{
  "id": "1973346613243552009",
  "url": "https://x.com/KynixXBT/status/1973346613243552009",
  "timestamp": "2025-10-01T11:17:50.000Z",
  "capturedAt": "2025-12-27T17:17:13.599Z",
  "author": "Kynix @KynixXBT",
  "authorName": "Kynix",
  "authorHandle": "@KynixXBT",
  "text": "Guess what the obvious manipulation dip that turned everyone bearish again has been fully recovered by $BTC.",
  "avatar": "kynixxbt/avatar/avatar.jpg",
  "avatarPath": "kynixxbt/avatar/avatar.jpg",
  "images": [],
  "jsonFile": "kynixxbt/tweets/1973346613243552009_2025-10-01-11-17-50.000Z/tweet.json",
  "mediaDir": "media",
  "userSlug": "kynixxbt"
}