{
  "id": "1956388404892942342",
  "url": "https://x.com/KynixXBT/status/1956388404892942342",
  "timestamp": "2025-08-15T16:11:58.000Z",
  "capturedAt": "2025-12-27T17:20:16.317Z",
  "author": "Kynix @KynixXBT",
  "authorName": "Kynix",
  "authorHandle": "@KynixXBT",
  "text": "I like how Doge and Avax have not yet made lower lows then yesterdays flush. Nice strength against BTC and ETH. Makes me more confident in my current 3x Swing Longs on both.",
  "avatar": "kynixxbt/avatar/avatar.jpg",
  "avatarPath": "kynixxbt/avatar/avatar.jpg",
  "images": [],
  "jsonFile": "kynixxbt/tweets/1956388404892942342_2025-08-15-16-11-58.000Z/tweet.json",
  "mediaDir": "media",
  "userSlug": "kynixxbt"
}