{
  "id": "1969453381883199673",
  "url": "https://x.com/KynixXBT/status/1969453381883199673",
  "timestamp": "2025-09-20T17:27:31.000Z",
  "capturedAt": "2025-12-27T17:17:32.377Z",
  "author": "Kynix @KynixXBT",
  "authorName": "Kynix",
  "authorHandle": "@KynixXBT",
  "text": "$ASTER did a 2x since this post advising caution. When CZ posted it at 0.17 it was an easy bet on crime, the question was if you saw it then. I saw it above 0.5 for the first time when all of CT was up millions already. Easy fade. Ridiculously overvalued by now. Don't roundtrip!",
  "avatar": "kynixxbt/avatar/avatar.jpg",
  "avatarPath": "kynixxbt/avatar/avatar.jpg",
  "images": [],
  "jsonFile": "kynixxbt/tweets/1969453381883199673_2025-09-20-17-27-31.000Z/tweet.json",
  "mediaDir": "media",
  "userSlug": "kynixxbt"
}