{
  "id": "1985175564102083013",
  "url": "https://x.com/KynixXBT/status/1985175564102083013",
  "timestamp": "2025-11-03T02:41:51.000Z",
  "capturedAt": "2025-12-27T17:13:41.846Z",
  "author": "Kynix @KynixXBT",
  "authorName": "Kynix",
  "authorHandle": "@KynixXBT",
  "text": "March: What is Trump doing with these tariffs. Is he retarded? And why is Crypto rugging so much? \nApril: It is so over. Trumps Plan is to crash the economy to easily refinance the state. This is the beginning of a long dark time for USA. Cryptos will go to zero. GTFO!",
  "avatar": "kynixxbt/avatar/avatar.jpg",
  "avatarPath": "kynixxbt/avatar/avatar.jpg",
  "images": [],
  "jsonFile": "kynixxbt/tweets/1985175564102083013_2025-11-03-02-41-51.000Z/tweet.json",
  "mediaDir": "media",
  "userSlug": "kynixxbt"
}