{
  "id": "1932984511626707439",
  "url": "https://x.com/KynixXBT/status/1932984511626707439",
  "timestamp": "2025-06-12T02:13:15.000Z",
  "capturedAt": "2025-12-27T17:28:43.751Z",
  "author": "Kynix @KynixXBT",
  "authorName": "Kynix",
  "authorHandle": "@KynixXBT",
  "text": "Current portfolio positioning:\nOrder by size\n\n- $ETH\n- $TAO\n- $SOL\n- $BONK\n- $LINK\n- $DOGE\n- $SUI\n- $HYPE\n\nAlso have some small positions in smaller MarketCap Sol and Base Memes.\nAnd a little bit of exposure to newer L1s. \n\nSo far up 2x from the April lows.",
  "avatar": "kynixxbt/avatar/avatar.jpg",
  "avatarPath": "kynixxbt/avatar/avatar.jpg",
  "images": [],
  "jsonFile": "kynixxbt/tweets/1932984511626707439_2025-06-12-02-13-15.000Z/tweet.json",
  "mediaDir": "media",
  "userSlug": "kynixxbt"
}